ukhotides/__init__.py
ukhotides/const.py
ukhotides/dataclasses.py
ukhotides/enums.py
ukhotides/exceptions.py
ukhotides/py.typed
ukhotides-1.1.2.dist-info/LICENSE
ukhotides-1.1.2.dist-info/METADATA
ukhotides-1.1.2.dist-info/WHEEL
ukhotides-1.1.2.dist-info/RECORD
