Metadata-Version: 2.1
Name: ukhotides
Version: 1.1.2
Summary: Python library for interfacing with the UKHO Admiralty Tidal API
License: MIT
Author: Ian Byrne
Author-email: ian.byrne@burnsie.com.au
Requires-Python: >=3.10,<4.0
Classifier: License :: OSI Approved :: MIT License
Classifier: Programming Language :: Python :: 3
Classifier: Programming Language :: Python :: 3.10
Classifier: Programming Language :: Python :: 3.11
Classifier: Programming Language :: Python :: 3.12
Classifier: Programming Language :: Python :: 3.13
Requires-Dist: aiohttp (>=3.10.11)
